frappysqlapibilling/__init__.py
frappysqlapibilling/usage_store.py
frappysqlapibilling-0.1.0.dist-info/LICENSE
frappysqlapibilling-0.1.0.dist-info/METADATA
frappysqlapibilling-0.1.0.dist-info/WHEEL
frappysqlapibilling-0.1.0.dist-info/top_level.txt
frappysqlapibilling-0.1.0.dist-info/RECORD
