Metadata-Version: 2.1
Name: frappysqlapibilling
Version: 0.1.0
Summary: SQL Store for the API Billing Backend
Home-page: https://github.com/ilfrich/frappy-py-sql-api-billing-store
Author: Peter Ilfrich
Author-email: das-peter@gmx.de
License: UNKNOWN
Platform: UNKNOWN
Requires-Dist: frappyapibilling
Requires-Dist: flask-sqlalchemy
Requires-Dist: sqlalchemy
